setup.cfg
setup.py
dblp2bib/__init__.py
dblp2bib/dblp2bib.py
dblp2bib.egg-info/PKG-INFO
dblp2bib.egg-info/SOURCES.txt
dblp2bib.egg-info/dependency_links.txt
dblp2bib.egg-info/requires.txt
dblp2bib.egg-info/top_level.txt