Metadata-Version: 1.1
Name: dblp2bib
Version: 0.0.2
Summary: A random test lib
Home-page: https://github.com/stefanthaler/dblp2bib
Author: Stefan Thaler
Author-email: s.m.thaler@tue.nl
License: UNKNOWN
Download-URL: https://github.com/stefanthaler/dblp2bib/tarball/0.0.2
Keywords: references,bibliography,dblp
Platform: UNKNOWN
